uncertainty/__init__.py
uncertainty/classifier.py
uncertainty/constants.py
uncertainty/helpers.py
uncertainty/sentence.py
uncertainty/word.py
uncertainty/data/__init__.py
uncertainty/data/download.py
uncertainty/data/merge.py
uncertainty/lib/nlp/__init__.py
uncertainty/lib/nlp/chunktagger.py
uncertainty/lib/nlp/lemmatizer.py
uncertainty/lib/nlp/postagger.py
uncertainty/lib/nlp/stemmer.py
uncertainty/lib/nlp/summarizer.py
uncertainty/lib/nlp/tokenizer.py
uncertainty/lib/nlp/verbs.txt
uncertainty/models/bclass.p
uncertainty/models/mclass.p
uncertainty/vectorizers/vectorizer.p
uncertainty-0.1.1.dist-info/DESCRIPTION.rst
uncertainty-0.1.1.dist-info/METADATA
uncertainty-0.1.1.dist-info/RECORD
uncertainty-0.1.1.dist-info/WHEEL
uncertainty-0.1.1.dist-info/metadata.json
uncertainty-0.1.1.dist-info/top_level.txt
